{
  "project_info": {
    "project_number": "746863863854",
    "firebase_url": "https://releave-1478208502521.firebaseio.com",
    "project_id": "releave-1478208502521",
    "storage_bucket": "releave-1478208502521.appspot.com"
  },
  "client": [
    {
      "client_info": {
        "mobilesdk_app_id": "1:746863863854:android:f4af06a504453606df97bf",
        "android_client_info": {
          "package_name": "com.releave.android"
        }
      },
      "oauth_client": [
        {
          "client_id": "746863863854-m48b2ic4m0tv2u7c67so0t1guke1tjlo.apps.googleusercontent.com",
          "client_type": 1,
          "android_info": {
            "package_name": "com.releave.android",
            "certificate_hash": "a507e06ead10e6028336e63a39f2d3911fa37257"
          }
        },
        {
          "client_id": "746863863854-rc16ip9sb4f73bcgarc26g6dc07ac5s1.apps.googleusercontent.com",
          "client_type": 3
        }
      ],
      "api_key": [
        {
          "current_key": "AIzaSyAvVNMUDd4mMYj5HPnAFvm8yrOHazjw_kQ"
        }
      ],
      "services": {
        "appinvite_service": {
          "other_platform_oauth_client": [
            {
              "client_id": "746863863854-rc16ip9sb4f73bcgarc26g6dc07ac5s1.apps.googleusercontent.com",
              "client_type": 3
            }
          ]
        }
      }
    }
  ],
  "configuration_version": "1"
}